mongomon/__init__.py
mongomon/__version__.py
mongomon-0.0.5.dist-info/WHEEL
mongomon-0.0.5.dist-info/METADATA
mongomon-0.0.5.dist-info/RECORD
