Metadata-Version: 2.1
Name: mongomon
Version: 0.0.5
Summary: A profiler for Python and mongodb
Home-page: https://github.com/jondot/mongomon
License: MIT
Keywords: pymongo,mongo,mongodb,monitoring,profiling
Author: Dotan Nahum
Author-email: jondotan@gmail.com
Classifier: License :: OSI Approved :: MIT License
Classifier: Programming Language :: Python :: 2
Classifier: Programming Language :: Python :: 2.7
Classifier: Programming Language :: Python :: 3
Classifier: Programming Language :: Python :: 3.4
Classifier: Programming Language :: Python :: 3.5
Classifier: Programming Language :: Python :: 3.6
Classifier: Programming Language :: Python :: 3.7
Provides-Extra: lint
Requires-Dist: attr (>=0.3.1,<0.4.0)
Requires-Dist: colored (>=1.3,<2.0)
Requires-Dist: pygments (>=2.3,<3.0)
Requires-Dist: six (>=1.12,<2.0)
Requires-Dist: toolz (>=0.9.0,<0.10.0)
Project-URL: Documentation, https://github.com/jondot/mongomon
Project-URL: Repository, https://github.com/jondot/mongomon
